cmake_converter/__init__.py
cmake_converter/context.py
cmake_converter/data_converter.py
cmake_converter/data_files.py
cmake_converter/dependencies.py
cmake_converter/flags.py
cmake_converter/main.py
cmake_converter/parser.py
cmake_converter/project_files.py
cmake_converter/project_variables.py
cmake_converter/utils.cmake
cmake_converter/utils.py
cmake_converter/writer.py
cmake_converter/visual_studio/Default.cmake
cmake_converter/visual_studio/DefaultCXX.cmake
cmake_converter/visual_studio/DefaultFortran.cmake
cmake_converter/visual_studio/context.py
cmake_converter/visual_studio/solution.py
cmake_converter/visual_studio/vcxproj/dependencies.py
cmake_converter/visual_studio/vcxproj/flags.py
cmake_converter/visual_studio/vcxproj/parser.py
cmake_converter/visual_studio/vcxproj/project_files.py
cmake_converter/visual_studio/vcxproj/project_variables.py
cmake_converter/visual_studio/vcxproj/utils.py
cmake_converter/visual_studio/vfproj/dependencies.py
cmake_converter/visual_studio/vfproj/flags.py
cmake_converter/visual_studio/vfproj/parser.py
cmake_converter/visual_studio/vfproj/project_files.py
cmake_converter/visual_studio/vfproj/project_variables.py
cmake_converter/visual_studio/vfproj/utils.py
cmake_converter-2.2.0.dist-info/METADATA
cmake_converter-2.2.0.dist-info/RECORD
cmake_converter-2.2.0.dist-info/WHEEL
cmake_converter-2.2.0.dist-info/entry_points.txt
cmake_converter-2.2.0.dist-info/top_level.txt
