Metadata-Version: 2.1
Name: cmake-converter
Version: 2.2.0
Summary: CMake converter for Visual Studio projects
Home-page: https://github.com/pavelliavonau/cmakeconverter
Author: Liavonau Pavel
Author-email: liavonlida@gmail.com
License: GNU Affero General Public License, version 3
Keywords: cmake sln vcxproj vfproj visual cpp fortran CMakeLists
Platform: UNKNOWN
Classifier: Development Status :: 5 - Production/Stable
Classifier: Environment :: Console
Classifier: Intended Audience :: End Users/Desktop
Classifier: Intended Audience :: Developers
Classifier: Intended Audience :: System Administrators
Classifier: License :: OSI Approved :: GNU General Public License v3 (GPLv3)
Classifier: Natural Language :: English
Classifier: Operating System :: OS Independent
Classifier: Programming Language :: Python :: 3
Classifier: Programming Language :: Python :: 3.6
Classifier: Programming Language :: Python :: 3.7
Classifier: Programming Language :: Python :: 3.8
Classifier: Programming Language :: Python :: 3.9
Classifier: Topic :: Software Development :: Build Tools
Classifier: Topic :: Software Development :: Code Generators
Classifier: Topic :: Software Development :: Compilers
Classifier: Topic :: Software Development :: Libraries
Requires-Python: >=3.6
Requires-Dist: lxml
Requires-Dist: colorama
